winz/__init__.py
winz/api.py
winz/middleware.py
winz/orm.py
winz/response.py
winz_simple_webframework-0.1.15.dist-info/METADATA
winz_simple_webframework-0.1.15.dist-info/WHEEL
winz_simple_webframework-0.1.15.dist-info/top_level.txt
winz_simple_webframework-0.1.15.dist-info/RECORD
