Metadata-Version: 2.1
Name: winz-simple-webframework
Version: 0.1.15
Summary: Python Web Framework built for learning purposes.
Home-page: https://github.com/yuwinzer/simple_python_web_framework/branches
Author: yuwinzer
Author-email: yuwinzer@example.com
License: MIT
Platform: UNKNOWN
Classifier: License :: OSI Approved :: MIT License
Classifier: Programming Language :: Python
Classifier: Programming Language :: Python :: 3
Classifier: Programming Language :: Python :: 3.10
Classifier: Programming Language :: Python :: Implementation :: CPython
Classifier: Programming Language :: Python :: Implementation :: PyPy
Requires-Python: >=3.10.0
Requires-Dist: Jinja2 (==3.1.2)
Requires-Dist: parse (==1.19.0)
Requires-Dist: requests (==2.27.1)
Requires-Dist: requests-wsgi-adapter (==0.4.1)
Requires-Dist: WebOb (==1.8.7)
Requires-Dist: whitenoise (==6.1.0)
